.gitignore
COPYING
Jenkinsfile
MANIFEST.in
README.md
build.parameters
setup.cfg
setup.py
applications/duphunter.desktop
bin/duphunter
duphunter.egg-info/PKG-INFO
duphunter.egg-info/SOURCES.txt
duphunter.egg-info/dependency_links.txt
duphunter.egg-info/not-zip-safe
duphunter.egg-info/top_level.txt
src/duphunter/MD5File.py
src/duphunter/__init__.py
src/duphunter/duphunter.ui