Metadata-Version: 1.1
Name: duphunter
Version: 0.1.5
Summary: An application that finds and lets you delete duplicate files
Home-page: http://github.com/Rudd-O/duphunter
Author: Manuel Amador (Rudd-O)
Author-email: rudd-o@rudd-o.com
License: GPL
Keywords: duplicate file management
Platform: UNKNOWN
Classifier: Intended Audience :: End Users/Desktop
Classifier: Intended Audience :: System Administrators
Classifier: License :: OSI Approved :: GNU General Public License (GPL)
Classifier: Operating System :: POSIX :: Linux
Classifier: Programming Language :: Python :: 2 :: Only
Classifier: Programming Language :: Python :: 2.7
Classifier: Topic :: Utilities
